s3app/__init__.py
s3app/config.py
s3app/s3_content_class.py
s3app/s3_content_rest.py
s3app/s3_content_view.py
s3app/s3_general_class.py
s3app/s3_general_error.py
s3app/s3_general_requests.py
s3app/s3_general_rest.py
s3app/s3_manage_class.py
s3app/s3_manage_rest.py
s3app/s3_manage_view.py
s3app/s3_sec.py
s3app/s3_sec_models.py
s3app/s3_sec_signals.py
s3app/s3_sec_views.py
s3app/s3_server.py
s3app/sqls/1_2_0.sql
s3app/sqls/sql.py
s3app/static/css/jsoneditor.css
s3app/static/css/main.css
s3app/static/css/img/jsoneditor-icons.svg
s3app/static/img/favicon.png
s3app/static/js/blockui.js
s3app/static/js/eventsContent.js
s3app/static/js/eventsManage.js
s3app/static/js/explorer.js
s3app/static/js/jsoneditor-minimalist.js
s3app/static/js/jsoneditor.js
s3app/static/js/manage.js
s3app/templates/__init__.py
s3app/templates/s3Content.html
s3app/templates/s3ManageGet.html
s3app/templates/s3ManageList.html
s3app/templates/appbuilder/_formhelpers.html
s3app/templates/appbuilder/base.html
s3app/templates/appbuilder/baselayout.html
s3app/templates/appbuilder/baselib.html
s3app/templates/appbuilder/flash.html
s3app/templates/appbuilder/footer.html
s3app/templates/appbuilder/index.html
s3app/templates/appbuilder/init.html
s3app/templates/appbuilder/navbar.html
s3app/templates/appbuilder/navbar_menu.html
s3app/templates/appbuilder/navbar_right.html
s3app/templates/appbuilder/general/alert.html
s3app/templates/appbuilder/general/confirm.html
s3app/templates/appbuilder/general/lib.html
s3app/templates/appbuilder/general/charts/chart.html
s3app/templates/appbuilder/general/charts/chart_time.html
s3app/templates/appbuilder/general/charts/jsonchart.html
s3app/templates/appbuilder/general/model/add.html
s3app/templates/appbuilder/general/model/edit.html
s3app/templates/appbuilder/general/model/edit_cascade.html
s3app/templates/appbuilder/general/model/left_master_detail.html
s3app/templates/appbuilder/general/model/list.html
s3app/templates/appbuilder/general/model/multiple_views.html
s3app-1.2.7.dist-info/LICENSE
s3app-1.2.7.dist-info/METADATA
s3app-1.2.7.dist-info/WHEEL
s3app-1.2.7.dist-info/entry_points.txt
s3app-1.2.7.dist-info/top_level.txt
s3app-1.2.7.dist-info/RECORD
