Metadata-Version: 2.1
Name: s3app
Version: 1.2.7
Summary: S3App simplifies the access to a S3Buckets with a provider independent web based frontend which allows the visualizing and the management of the content of S3 buckets with an S3 provider independent web application.
Author-email: Jörn Kleinbub <joern.kleinbub@yotron.de>
License: Apache License
Project-URL: A3App-Homepage, https://www.yotron.de/s3app/
Project-URL: Provider-Homepage, https://www.yotron.de/
Project-URL: Repository, https://github.com/yotron/s3app/
Project-URL: HELM-Project, https://artifacthub.io/packages/helm/yotron-helm-charts/s3app
Keywords: s3,manager,app,web
Classifier: License :: OSI Approved :: Apache Software License
Classifier: Programming Language :: Python
Classifier: Programming Language :: Python :: 3
Requires-Python: >=3.9
License-File: LICENSE
Requires-Dist: Flask >=2.2.0
Requires-Dist: Flask-Login >=0.1.1
Requires-Dist: Flask-AppBuilder >=4.1.4
Requires-Dist: Flask-Session >=0.4.0
Requires-Dist: boto3 >=1.24.0
Requires-Dist: flask-restful >=0.2.12
Requires-Dist: blinker >=1.5.0
Requires-Dist: psycopg2-binary >=2.9.3
Requires-Dist: waitress >=2.1.2
Requires-Dist: python-dotenv >=0.21.0
Requires-Dist: python-ldap >=3.4.3
